{"_type":"export","__export_format":4,"__export_date":"2024-04-13T18:09:21.919Z","__export_source":"insomnia.desktop.app:v8.6.1","resources":[{"_id":"req_8d764207d6fb44d9a5634591df009e13","parentId":"fld_714f732a361646f38ddeb73597559602","modified":1713025659337,"created":1713025613012,"url":"localhost:3333/settings/orders","name":"Get Order Settings","description":"","method":"GET","body":{},"parameters":[],"headers":[{"name":"User-Agent","value":"insomnia/8.6.1"}],"authentication":{},"metaSortKey":-1713025613012,"isPrivate":false,"pathParameters":[],"settingStoreCookies":true,"settingSendCookies":true,"settingDisableRenderRequestBody":false,"settingEncodeUrl":true,"settingRebuildPath":true,"settingFollowRedirects":"global","_type":"request"},{"_id":"fld_714f732a361646f38ddeb73597559602","parentId":"fld_c4d33e835a344870a304a597d3dd33e9","modified":1713025610991,"created":1713025610991,"name":"Order Settings","description":"","environment":{},"environmentPropertyOrder":null,"metaSortKey":-1713025610991,"_type":"request_group"},{"_id":"fld_c4d33e835a344870a304a597d3dd33e9","parentId":"wrk_7414571e668047b7a090836829e8046d","modified":1713024391981,"created":1713024391981,"name":"Settings","description":"","environment":{},"environmentPropertyOrder":null,"metaSortKey":-1713024391981,"_type":"request_group"},{"_id":"wrk_7414571e668047b7a090836829e8046d","parentId":null,"modified":1712676585784,"created":1712676585784,"name":"AI-Product-Generator","description":"","scope":"collection","_type":"workspace"},{"_id":"req_302147df596d4e8ab1ec514aedb9cca3","parentId":"fld_714f732a361646f38ddeb73597559602","modified":1713025915444,"created":1713025687930,"url":"localhost:3333/settings/orders","name":"Add Order Settings","description":"","method":"POST","body":{"mimeType":"application/json","text":"{\n\t\"orderNum\": 3,\n\t\"productCount\": [1, 4, 5],\n\t\"subject\": \"random prompt\"\n}"},"parameters":[],"headers":[{"name":"Content-Type","value":"application/json"},{"name":"User-Agent","value":"insomnia/8.6.1"}],"authentication":{},"metaSortKey":-1712855697399,"isPrivate":false,"pathParameters":[],"settingStoreCookies":true,"settingSendCookies":true,"settingDisableRenderRequestBody":false,"settingEncodeUrl":true,"settingRebuildPath":true,"settingFollowRedirects":"global","_type":"request"},{"_id":"req_fce45109c1db4756a904b7d5a0f4f642","parentId":"fld_a99bcb9dfcfa4cd8ba05d9935db7633e","modified":1713025858683,"created":1713025831688,"url":"localhost:3333/settings/products","name":"Get Product Settings","description":"","method":"GET","body":{},"parameters":[],"headers":[{"name":"User-Agent","value":"insomnia/8.6.1"}],"authentication":{},"metaSortKey":-1713025613012,"isPrivate":false,"pathParameters":[],"settingStoreCookies":true,"settingSendCookies":true,"settingDisableRenderRequestBody":false,"settingEncodeUrl":true,"settingRebuildPath":true,"settingFollowRedirects":"global","_type":"request"},{"_id":"fld_a99bcb9dfcfa4cd8ba05d9935db7633e","parentId":"fld_c4d33e835a344870a304a597d3dd33e9","modified":1713025831687,"created":1713025831687,"name":"Product Settings","description":"","environment":{},"environmentPropertyOrder":null,"metaSortKey":-1713025001486,"_type":"request_group"},{"_id":"req_3f8f1e16991e49258bf9cf938178c056","parentId":"fld_a99bcb9dfcfa4cd8ba05d9935db7633e","modified":1713026057490,"created":1713025831690,"url":"localhost:3333/settings/products","name":"Add Product Settings","description":"","method":"POST","body":{"mimeType":"application/json","text":"{\n\t\"productCount\": 1,\n\t\"subject\": \"some random prompt\"\n}"},"parameters":[],"headers":[{"name":"Content-Type","value":"application/json"},{"name":"User-Agent","value":"insomnia/8.6.1"}],"authentication":{},"metaSortKey":-1712855697399,"isPrivate":false,"pathParameters":[],"settingStoreCookies":true,"settingSendCookies":true,"settingDisableRenderRequestBody":false,"settingEncodeUrl":true,"settingRebuildPath":true,"settingFollowRedirects":"global","_type":"request"},{"_id":"req_2283c3a50a9f4942a1e814f481ede76e","parentId":"fld_561736aac38945d5b774d476401aa7ae","modified":1713025589713,"created":1712685781786,"url":"localhost:3333/orders","name":"Get All Orders","description":"","method":"GET","body":{},"parameters":[],"headers":[{"name":"User-Agent","value":"insomnia/8.6.1"}],"authentication":{},"metaSortKey":-1712685781786,"isPrivate":false,"pathParameters":[],"settingStoreCookies":true,"settingSendCookies":true,"settingDisableRenderRequestBody":false,"settingEncodeUrl":true,"settingRebuildPath":true,"settingFollowRedirects":"global","_type":"request"},{"_id":"fld_561736aac38945d5b774d476401aa7ae","parentId":"wrk_7414571e668047b7a090836829e8046d","modified":1712685777584,"created":1712685777584,"name":"Orders","description":"","environment":{},"environmentPropertyOrder":null,"metaSortKey":-1712685777584,"_type":"request_group"},{"_id":"req_ff1597a6e2b4425d970c81b76780be85","parentId":"fld_561736aac38945d5b774d476401aa7ae","modified":1712765233507,"created":1712685839356,"url":"localhost:3333/orders/product-search/41e9b7fc-0544-416f-8bb9-25453b7939c2","name":"Find Products For Order","description":"","method":"GET","body":{},"parameters":[],"headers":[{"name":"User-Agent","value":"insomnia/8.6.1"}],"authentication":{},"metaSortKey":-1712683002141,"isPrivate":false,"pathParameters":[],"settingStoreCookies":true,"settingSendCookies":true,"settingDisableRenderRequestBody":false,"settingEncodeUrl":true,"settingRebuildPath":true,"settingFollowRedirects":"global","_type":"request"},{"_id":"req_fef0c1a1214e44c8b76ec5792635f737","parentId":"fld_561736aac38945d5b774d476401aa7ae","modified":1712761470843,"created":1712761431287,"url":"localhost:3333/orders/order-search/897eed81-7bc3-4406-96fc-bb5965b7068d","name":"Find Orders For Product","description":"","method":"GET","body":{},"parameters":[],"headers":[{"name":"User-Agent","value":"insomnia/8.6.1"}],"authentication":{},"metaSortKey":-1712682654685.375,"isPrivate":false,"pathParameters":[],"settingStoreCookies":true,"settingSendCookies":true,"settingDisableRenderRequestBody":false,"settingEncodeUrl":true,"settingRebuildPath":true,"settingFollowRedirects":"global","_type":"request"},{"_id":"req_d33118f112544af0a0ca798ae4abd832","parentId":"fld_561736aac38945d5b774d476401aa7ae","modified":1712820239788,"created":1712685875883,"url":"localhost:3333/orders/add","name":"Add Order","description":"","method":"POST","body":{"mimeType":"application/json","text":"{\n\t\"productSKUs\": [\"cluuwq2c00005ohrhsayzbupm\", \"cluuwq4g00006ohrhsgilmngw\"]\n}"},"parameters":[],"headers":[{"name":"Content-Type","value":"application/json"},{"name":"User-Agent","value":"insomnia/8.6.1"}],"authentication":{},"metaSortKey":-1712682307229.75,"isPrivate":false,"pathParameters":[],"settingStoreCookies":true,"settingSendCookies":true,"settingDisableRenderRequestBody":false,"settingEncodeUrl":true,"settingRebuildPath":true,"settingFollowRedirects":"global","_type":"request"},{"_id":"req_95519d6b9dc444c1ab1c149af4b0f5d6","parentId":"fld_561736aac38945d5b774d476401aa7ae","modified":1712765301504,"created":1712685862594,"url":"localhost:3333/orders/delete/29a7266b-5ee5-48ef-b01f-a14116faba5d","name":"Delete Order","description":"","method":"DELETE","body":{},"parameters":[],"headers":[{"name":"User-Agent","value":"insomnia/8.6.1"}],"authentication":{},"metaSortKey":-1712681612318.5,"isPrivate":false,"pathParameters":[],"settingStoreCookies":true,"settingSendCookies":true,"settingDisableRenderRequestBody":false,"settingEncodeUrl":true,"settingRebuildPath":true,"settingFollowRedirects":"global","_type":"request"},{"_id":"req_81543d2d8cfd48f5abc3026b40af469d","parentId":"fld_66f7b8e99c9c4b37a335930aa5fa87f8","modified":1712851416971,"created":1712680222496,"url":"localhost:3333/tags/cluuwq4g00006ohrhsgilmngw","name":"Get All Tags For Product","description":"","method":"GET","body":{},"parameters":[],"headers":[{"name":"User-Agent","value":"insomnia/8.6.1"}],"authentication":{},"metaSortKey":-1712680222496,"isPrivate":false,"pathParameters":[],"settingStoreCookies":true,"settingSendCookies":true,"settingDisableRenderRequestBody":false,"settingEncodeUrl":true,"settingRebuildPath":true,"settingFollowRedirects":"global","_type":"request"},{"_id":"fld_66f7b8e99c9c4b37a335930aa5fa87f8","parentId":"wrk_7414571e668047b7a090836829e8046d","modified":1712680220085,"created":1712680220085,"name":"Tags","description":"","environment":{},"environmentPropertyOrder":null,"metaSortKey":-1712680220085,"_type":"request_group"},{"_id":"req_1262591fc4de4d6d8d6baf9ff2527f80","parentId":"fld_66f7b8e99c9c4b37a335930aa5fa87f8","modified":1712835009194,"created":1712681514160,"url":"localhost:3333/tags/add/cluuwq2c00005ohrhsayzbupm","name":"Add Tag To Product","description":"","method":"POST","body":{"mimeType":"application/json","text":"{\n\t\"color\": \"#4E4BA4\",\n\t\"message\": \"This is a looooooong tag\"\n}"},"parameters":[],"headers":[{"name":"Content-Type","value":"application/json"},{"name":"User-Agent","value":"insomnia/8.6.1"}],"authentication":{},"metaSortKey":-1712680203659.5,"isPrivate":false,"pathParameters":[],"settingStoreCookies":true,"settingSendCookies":true,"settingDisableRenderRequestBody":false,"settingEncodeUrl":true,"settingRebuildPath":true,"settingFollowRedirects":"global","_type":"request"},{"_id":"req_bfba7569a70d4477b47c933c80da9482","parentId":"fld_66f7b8e99c9c4b37a335930aa5fa87f8","modified":1712685758399,"created":1712685628849,"url":"localhost:3333/tags/delete/75ab09fd-7a25-4b7e-a072-8250b02d28e9","name":"Delete Tag","description":"","method":"DELETE","body":{},"parameters":[],"headers":[{"name":"User-Agent","value":"insomnia/8.6.1"}],"authentication":{},"metaSortKey":-1712680194241.25,"isPrivate":false,"pathParameters":[],"settingStoreCookies":true,"settingSendCookies":true,"settingDisableRenderRequestBody":false,"settingEncodeUrl":true,"settingRebuildPath":true,"settingFollowRedirects":"global","_type":"request"},{"_id":"req_feb4c8bfcfb44471b340f1e776f88aaa","parentId":"fld_f1988ba9683a489fa8194ea2a4b66310","modified":1712680862919,"created":1712676648959,"url":"localhost:3333/products","name":"Get All Products","description":"","method":"GET","body":{},"parameters":[],"headers":[{"name":"User-Agent","value":"insomnia/8.6.1"}],"authentication":{},"metaSortKey":-1712680184823,"isPrivate":false,"pathParameters":[],"settingStoreCookies":true,"settingSendCookies":true,"settingDisableRenderRequestBody":false,"settingEncodeUrl":true,"settingRebuildPath":true,"settingFollowRedirects":"global","_type":"request"},{"_id":"fld_f1988ba9683a489fa8194ea2a4b66310","parentId":"wrk_7414571e668047b7a090836829e8046d","modified":1712680156303,"created":1712680156303,"name":"Products","description":"","environment":{},"environmentPropertyOrder":null,"metaSortKey":-1712680156303,"_type":"request_group"},{"_id":"req_82763c83475149bb81936beb0c57fa96","parentId":"fld_f1988ba9683a489fa8194ea2a4b66310","modified":1712753525117,"created":1712753516888,"url":"localhost:3333/products/deleted-products","name":"Get All Deleted Products","description":"","method":"GET","body":{},"parameters":[],"headers":[{"name":"User-Agent","value":"insomnia/8.6.1"}],"authentication":{},"metaSortKey":-1712680184773,"isPrivate":false,"pathParameters":[],"settingStoreCookies":true,"settingSendCookies":true,"settingDisableRenderRequestBody":false,"settingEncodeUrl":true,"settingRebuildPath":true,"settingFollowRedirects":"global","_type":"request"},{"_id":"req_2da2d4e944ad460fa135565af13bbb8a","parentId":"fld_f1988ba9683a489fa8194ea2a4b66310","modified":1712855333761,"created":1712677158825,"url":"localhost:3333/products/add-product","name":"Add Product","description":"","method":"POST","body":{"mimeType":"application/json","text":"{\n\t\t\"name\": \"test4\",\n\t\t\"count\": 2,\n\t\t\"price\": 100,\n\t\t\"providerPrice\": 80,\n\t\t\"brand\": \"testBrand2\",\n\t\t\"imageUrl\": \"\",\n\t\t\"notes\": \"A good product for an excellent price\",\n\t\t\"tags\": []\n\t}"},"parameters":[],"headers":[{"name":"Content-Type","value":"application/json"},{"name":"User-Agent","value":"insomnia/8.6.1"}],"authentication":{},"metaSortKey":-1712680184723,"isPrivate":false,"pathParameters":[],"settingStoreCookies":true,"settingSendCookies":true,"settingDisableRenderRequestBody":false,"settingEncodeUrl":true,"settingRebuildPath":true,"settingFollowRedirects":"global","_type":"request"},{"_id":"req_8b07ef63181f4d00bebc72fc5c8d96d5","parentId":"fld_f1988ba9683a489fa8194ea2a4b66310","modified":1712851398286,"created":1712678271365,"url":"localhost:3333/products/update/cluuwq4g00006ohrhsgilmngw","name":"Update Product","description":"","method":"PUT","body":{"mimeType":"application/json","text":"{\n\t\"SKU\": \"cluuwq4g00006ohrhsgilmngw\",\n\t\t\"name\": \"test3\",\n\t\t\"count\": 2,\n\t\t\"price\": 100,\n\t\t\"providerPrice\": 80,\n\t\t\"brand\": \"testBrand2\",\n\t\t\"imageUrl\": null,\n\t\t\"notes\": \"A good product for an excellent price\",\n\t\t\"deleted\": false,\n\t\t\"createdAt\": \"2024-04-11T07:17:47.905Z\",\n\t\t\"updatedAt\": \"2024-04-11T07:17:47.905Z\",\n\t\t\"tags\": [\n\t\t\t{\n\t\t\t\t\"SKU\": \"cluuwud8i000johrh28oijpg5\",\n\t\t\t\t\"color\": \"#4E4BA4\",\n\t\t\t\t\"message\": \"This is a tag\",\n\t\t\t\t\"productSKU\": \"cluuwq4g00006ohrhsgilmngw\",\n\t\t\t\t\"createdAt\": \"2024-04-11T07:21:05.923Z\",\n\t\t\t\t\"updatedAt\": \"2024-04-11T07:21:05.923Z\"\n\t\t\t}\n\t\t]\n}"},"parameters":[{"id":"pair_340e43183b4b4761b974413b3bcdb327","name":"","value":"","description":""}],"headers":[{"name":"Content-Type","value":"application/json"},{"name":"User-Agent","value":"insomnia/8.6.1"}],"authentication":{},"metaSortKey":-1712680184523,"isPrivate":false,"pathParameters":[],"settingStoreCookies":true,"settingSendCookies":true,"settingDisableRenderRequestBody":false,"settingEncodeUrl":true,"settingRebuildPath":true,"settingFollowRedirects":"global","_type":"request"},{"_id":"req_9639cb73af8c4993b98980a721b3116e","parentId":"fld_f1988ba9683a489fa8194ea2a4b66310","modified":1712764612909,"created":1712679922287,"url":"localhost:3333/products/restore/f7d56da9-d079-44cc-85bd-48fe1ef560eb","name":"Restore Product","description":"","method":"PATCH","body":{},"parameters":[],"headers":[{"name":"User-Agent","value":"insomnia/8.6.1"}],"authentication":{},"metaSortKey":-1712680184423,"isPrivate":false,"pathParameters":[],"settingStoreCookies":true,"settingSendCookies":true,"settingDisableRenderRequestBody":false,"settingEncodeUrl":true,"settingRebuildPath":true,"settingFollowRedirects":"global","_type":"request"},{"_id":"req_509587396b6c4e05ad0ebbc65d1d3d7a","parentId":"fld_f1988ba9683a489fa8194ea2a4b66310","modified":1712764819142,"created":1712677677418,"url":"localhost:3333/products/71738cb8-a4a6-4541-ba89-1ecd6f7af405","name":"Delete Product","description":"","method":"DELETE","body":{},"parameters":[],"headers":[{"name":"User-Agent","value":"insomnia/8.6.1"}],"authentication":{},"metaSortKey":-1712680184323,"isPrivate":false,"pathParameters":[],"settingStoreCookies":true,"settingSendCookies":true,"settingDisableRenderRequestBody":false,"settingEncodeUrl":true,"settingRebuildPath":true,"settingFollowRedirects":"global","_type":"request"},{"_id":"env_7cfeb95f9f4af41c331437852b1b84e2d29d19e1","parentId":"wrk_7414571e668047b7a090836829e8046d","modified":1712676585787,"created":1712676585787,"name":"Base Environment","data":{},"dataPropertyOrder":null,"color":null,"isPrivate":false,"metaSortKey":1712676585787,"_type":"environment"},{"_id":"jar_7cfeb95f9f4af41c331437852b1b84e2d29d19e1","parentId":"wrk_7414571e668047b7a090836829e8046d","modified":1713028450742,"created":1712676585788,"name":"Default Jar","cookies":[{"key":"__cf_bm","value":"D4BUObOJjYUu.oa4B8hKxgJG7_cJhCQHhm5yc5uskiA-1713028449-1.0.1.1-t7KTJojdWNTGVE6dZOs1SauuFJOyIBNT7K7oyDBjCrS8O_OEG1_ICclth0WWVv5D5Po4nrz.95kB0MAEVzbVtw","expires":"2024-04-13T17:44:09.000Z","domain":"pexels.com","path":"/","secure":true,"httpOnly":true,"hostOnly":false,"creation":"2024-04-13T17:14:10.737Z","lastAccessed":"2024-04-13T17:14:10.737Z","sameSite":"none","id":"387a62e3-e987-4c55-95c8-3e7b0d6f3b8d"}],"_type":"cookie_jar"}]}